stv_copy/main.py
stv_copy-0.0.1.dist-info/METADATA
stv_copy-0.0.1.dist-info/WHEEL
stv_copy-0.0.1.dist-info/entry_points.txt
stv_copy-0.0.1.dist-info/top_level.txt
stv_copy-0.0.1.dist-info/RECORD
