Metadata-Version: 2.4
Name: stv_copy
Version: 0.0.1
Summary: 文本文件内容复制工具
Author-email: "星灿长风v(StarWindv)" <starwindv.stv@gmail.com>
License: MIT
Project-URL: Homepage, https://github.com/StarWindv
Classifier: Programming Language :: Python :: 3
Requires-Python: >=3.7
